eth_to_imx_metadata_converter
