Metadata-Version: 1.1
Name: eth-to-imx-metadata-converter
Version: 0.1.1
Summary: Tool for converting ERC-721 metadata format into Immutable X compatible format
Home-page: https://github.com/dee-gmiterko/eth-to-imx-metadata-converter
Author: Dominik Gmiterko
Author-email: d.gmiterko@gmail.com
License: BSD
Platform: any
Classifier: Development Status :: 4 - Beta
Classifier: Environment :: Console
Classifier: Intended Audience :: Developers
Classifier: License :: OSI Approved :: BSD License
Classifier: Operating System :: POSIX
Classifier: Operating System :: MacOS
Classifier: Operating System :: Unix
Classifier: Operating System :: Microsoft :: Windows
Classifier: Programming Language :: Python
Classifier: Programming Language :: Python :: 2
Classifier: Programming Language :: Python :: 3
Classifier: Topic :: Software Development :: Libraries :: Python Modules
